ander/__init__.py
ander/cli.py
ander-0.2.0.dist-info/entry_points.txt
ander-0.2.0.dist-info/LICENSE
ander-0.2.0.dist-info/WHEEL
ander-0.2.0.dist-info/METADATA
ander-0.2.0.dist-info/RECORD
